ubuf.py
ubuf-0.0.2.data/data/io/io.hpp
ubuf-0.0.2.data/data/io/io.js
ubuf-0.0.2.dist-info/METADATA
ubuf-0.0.2.dist-info/WHEEL
ubuf-0.0.2.dist-info/entry_points.txt
ubuf-0.0.2.dist-info/top_level.txt
ubuf-0.0.2.dist-info/RECORD
