Metadata-Version: 2.1
Name: ubuf
Version: 0.0.2
Summary: Generate protocols for C++ and JS
Home-page: https://github.com/louisabraham/ubuf
Author: Louis Abraham
Author-email: louis.abraham@yahoo.fr
License: UNKNOWN
Platform: UNKNOWN
Classifier: Development Status :: 3 - Alpha
Classifier: Intended Audience :: Developers
Classifier: Topic :: Software Development :: Code Generators
Classifier: License :: OSI Approved :: MIT License
Requires-Python: >=3.7
Requires-Dist: pyyaml
